README.rst
setup.py
django_testclient_extensions.egg-info/PKG-INFO
django_testclient_extensions.egg-info/SOURCES.txt
django_testclient_extensions.egg-info/dependency_links.txt
django_testclient_extensions.egg-info/requires.txt
django_testclient_extensions.egg-info/top_level.txt
testclient_extensions/__init__.py
testclient_extensions/client.py
testclient_extensions/encoder.py